Workbook
Name NativeTimeline_Order_Date: #N/A
Name Slicer_Customer_Segment: #N/A
Name Slicer_Order_Date: #N/A
Name Slicer_Order_Status: #N/A
Name Slicer_Region: #N/A

Sheet Sales_transactions_data
A1: Order_ID | B1: Order_Date | C1: Customer_ID | D1: Customer_Segment | E1: Region | F1: Country | G1: Product_ID | H1: Product_Category | I1: Product_Name | J1: Quantity | K1: Unit_Price | L1: Unit_Cost | M1: Revenue | N1: Cost | O1: Profit | P1: Sales_Rep | Q1: Payment_Method | R1: Order_Status
A2: ORD-10001 | B2: 01/01/2024 | C2: CUST-201 | D2: Corporate | E2: North America | F2: United States | G2: Prd-01 | H2: Electronics | I2: Laptop Pro 14 | J2: 7 | K2: 1200 | L2: 900 | M2: 8400 | N2: 6300 | O2: 2100 | P2: Alex Morgan | Q2: Card | R2: Completed
A3: ORD-10002 | B3: 02/01/2024 | C3: CUST-305 | D3: Consumer | E3: Europe | F3: Germany | G3: Prd-02 | H3: Electronics | I3: Tablet Air 10 | J3: 5 | K3: 600 | L3: 520 | M3: 3000 | N3: 2600 | O3: 400 | P3: Daniel Smith | Q3: Card | R3: Completed
A4: ORD-10003 | B4: 03/01/2024 | C4: CUST-178 | D4: Small Business | E4: Asia-Pacific | F4: Australia | G4: Prd-03 | H4: Furniture | I4: Office Chair Deluxe | J4: 3 | K4: 320 | L4: 250 | M4: 960 | N4: 750 | O4: 210 | P4: Sophie Klein | Q4: Cash | R4: Completed
A5: ORD-10004 | B5: 04/01/2024 | C5: CUST-412 | D5: Corporate | E5: Middle East | F5: United Arab Emirates | G5: Prd-04 | H5: Furniture | I5: Standing Desk Pro | J5: 3 | K5: 850 | L5: 700 | M5: 2550 | N5: 2100 | O5: 450 | P5: Marie Dubois | Q5: Card | R5: Returned
A6: ORD-10005 | B6: 05/01/2024 | C6: CUST-256 | D6: Consumer | E6: South America | F6: Brazil | G6: Prd-05 | H6: Electronics | I6: Wireless Monitor 27 | J6: 3 | K6: 450 | L6: 380 | M6: 1350 | N6: 1140 | O6: 210 | P6: Jan De Vries | Q6: Transfer | R6: Pending
A7: ORD-10006 | B7: 06/01/2024 | C7: CUST-389 | D7: Small Business | E7: Europe | F7: France | G7: Prd-06 | H7: Office Supply | I7: Wireless Mouse | J7: 2 | K7: 25 | L7: 18 | M7: 50 | N7: 36 | O7: 14 | P7: Liam Chen | Q7: Transfer | R7: Completed
A8: ORD-10007 | B8: 07/01/2024 | C8: CUST-144 | D8: Corporate | E8: North America | F8: Canada | G8: Prd-07 | H8: Office Supplies | I8: Paper Ream A4 | J8: 4 | K8: 6 | L8: 3 | M8: 24 | N8: 12 | O8: 12 | P8: Wei Zhang | Q8: Card | R8: Completed
A9: ORD-10008 | B9: 08/01/2024 | C9: CUST-198 | D9: Consumer | E9: Asia-Pacific | F9: Singapore | G9: Prd-08 | H9: Furniture | I9: Conference Table | J9: 4 | K9: 2200 | L9: 2000 | M9: 8800 | N9: 8000 | O9: 800 | P9: Omar Hassan | Q9: Transfer | R9: Pending
A10: ORD-10009 | B10: 09/01/2024 | C10: CUST-501 | D10: Corporate | E10: Europe | F10: Netherlands | G10: Prd-09 | H10: Office Supplies | I10: Ink Cartridge Xl | J10: 4 | K10: 45 | L10: 40 | M10: 180 | N10: 160 | O10: 20 | P10: Fahad Al Saud | Q10: Card | R10: Completed
A11: ORD-10010 | B11: 10/01/2024 | C11: CUST-322 | D11: Small Business | E11: Middle East | F11: Saudi Arabia | G11: Prd-01 | H11: Electronics | I11: Laptop Pro 14 | J11: 3 | K11: 1200 | L11: 900 | M11: 3600 | N11: 2700 | O11: 900 | P11: Lucas Pereira | Q11: Cash | R11: Completed
A12: ORD-10011 | B12: 11/01/2024 | C12: CUST-201 | D12: Corporate | E12: North America | F12: United States | G12: Prd-02 | H12: Electronics | I12: Tablet Air 10 | J12: 4 | K12: 600 | L12: 520 | M12: 2400 | N12: 2080 | O12: 320 | P12: Alex Morgan | Q12: Cash | R12: Completed
A13: ORD-10012 | B13: 12/01/2024 | C13: CUST-305 | D13: Consumer | E13: Europe | F13: Germany | G13: Prd-03 | H13: Furniture | I13: Office Chair Deluxe | J13: 4 | K13: 320 | L13: 250 | M13: 1280 | N13: 1000 | O13: 280 | P13: Daniel Smith | Q13: Cash | R13: Returned
... A601: ORD-10600 | B601: 22/08/2024 | C601: CUST-322 | D601: Small Business | E601: Middle East | F601: Saudi Arabia | G601: Prd-06 | H601: Office Supply | I601: Wireless Mouse | J601: 5 | K601: 25 | L601: 18 | M601: 125 | N601: 90 | O601: 35 | P601: Lucas Pereira | Q601: Card | R601: Completed

Sheet Products
A1: Product_ID | B1: Product_Name | C1: Product_Category | D1: Unit_Cost | E1: Unit_Price
A2: PRD-01 | B2: Laptop Pro 14 | C2: Electronics | D2: 900 | E2: 1200
A3: PRD-02 | B3: Tablet Air 10 | C3: Electronics | D3: 520 | E3: 600
A4: PRD-03 | B4: Office Chair Deluxe | C4: Furniture | D4: 250 | E4: 320
A5: PRD-04 | B5: Standing Desk Pro | C5: Furniture | D5: 700 | E5: 850
A6: PRD-05 | B6: Wireless Monitor 27 | C6: Electronics | D6: 380 | E6: 450
A7: PRD-06 | B7: Wireless Mouse | C7: Office Supply | D7: 18 | E7: 25
A8: PRD-07 | B8: Paper Ream A4 | C8: Office Supplies | D8: 3 | E8: 6
A9: PRD-08 | B9: Conference Table | C9: Furniture | D9: 2000 | E9: 2200
A10: PRD-09 | B10: Ink Cartridge Xl | C10: Office Supplies | D10: 40 | E10: 45

Sheet Customers
A1: Customer_ID | B1: Customer_Segment | C1: Region | D1: Country
A2: CUST-201 | B2: Corporate | C2: North America | D2: United States
A3: CUST-305 | B3: Consumer | C3: Europe | D3: Germany
A4: CUST-178 | B4: Small Business | C4: Asia-Pacific | D4: Australia
A5: CUST-412 | B5: Corporate | C5: Middle East | D5: United Arab Emirates
A6: CUST-256 | B6: Consumer | C6: South America | D6: Brazil
A7: CUST-389 | B7: Small Business | C7: Europe | D7: France
A8: CUST-144 | B8: Corporate | C8: North America | D8: Canada
A9: CUST-198 | B9: Consumer | C9: Asia-Pacific | D9: Singapore
A10: CUST-501 | B10: Corporate | C10: Europe | D10: Netherlands
A11: CUST-322 | B11: Small Business | C11: Middle East | D11: Saudi Arabia
A12: CUST-411 | B12: Corporate | C12: Asia-Pacific | D12: Japan
... A14: CUST-633 | B14: Small Business | C14: South America | D14: Argentina

Sheet Sales_reps
A1: Sales_Rep | B1: Region | C1: Monthly_Target | D1: Column1
A2: Alex Morgan | B2: North America | C2: 120000 | D2: =_xlfn.XLOOKUP(A2,$A$2:$A$11,Pivot_tables!$B$37:$B$46) -> 176113
A3: Daniel Smith | B3: North America | C3: 100000 | D3: =_xlfn.XLOOKUP(A3,$A$2:$A$11,Pivot_tables!$B$37:$B$46) -> 134249
A4: Sophie Klein | B4: Europe | C4: 90000 | D4: =_xlfn.XLOOKUP(A4,$A$2:$A$11,Pivot_tables!$B$37:$B$46) -> 164835
A5: Marie Dubois | B5: Europe | C5: 88000 | D5: =_xlfn.XLOOKUP(A5,$A$2:$A$11,Pivot_tables!$B$37:$B$46) -> 163022
A6: Jan De Vries | B6: Europe | C6: 87000 | D6: =_xlfn.XLOOKUP(A6,$A$2:$A$11,Pivot_tables!$B$37:$B$46) -> 156541
A7: Liam Chen | B7: Asia-Pacific | C7: 85000 | D7: =_xlfn.XLOOKUP(A7,$A$2:$A$11,Pivot_tables!$B$37:$B$46) -> 136519
A8: Wei Zhang | B8: Asia-Pacific | C8: 92000 | D8: =_xlfn.XLOOKUP(A8,$A$2:$A$11,Pivot_tables!$B$37:$B$46) -> 165478
A9: Omar Hassan | B9: Middle East | C9: 95000 | D9: =_xlfn.XLOOKUP(A9,$A$2:$A$11,Pivot_tables!$B$37:$B$46) -> 139581
A10: Fahad Al Saud | B10: Middle East | C10: 98000 | D10: =_xlfn.XLOOKUP(A10,$A$2:$A$11,Pivot_tables!$B$37:$B$46) -> 58932
A11: Lucas Pereira | B11: South America | C11: 70000 | D11: =_xlfn.XLOOKUP(A11,$A$2:$A$11,Pivot_tables!$B$37:$B$46) -> 91607

Sheet Business_Questions
E5: Business Questions | F5: Answers
D7: 1 | E7: How is revenue and profit trending over time? | F7: Revenue shows moderate growth with volatility, while profit declines notably in Sep–Oct, suggesting margin pressure or increased costs.
D8: 2 | E8: Which products generete high revenue but low profit? | F8: Conference Table and Standing Desk Pro drive high revenue but deliver comparatively lower profit margins than smaller office supplies.
D9: 3 | E9: Which regions are underperforming on profit margins? | F9: Europe generates the highest revenue but exhibits margin pressure compared to North America.
D10: 4 | E10: Which sales reps are exceeding or missing targets? | F10: Most reps meet targets in early months, while performance declines in later months, particularly in Q3.
D11: 5 | E11: Which customer segments are most profitable? | F11: Corporate customers generate the highest profit contribution, followed by Small Business, with Consumer showing lower margins.

Sheet Analysis
B4: Core KPIs
B5: Total Revenue | C5: =Pivot_tables!F13 -> 1556176
B6: Total Cost | C6: =C5-C7 -> 1310306
B7: Total Profit | C7: =Pivot_tables!G13 -> 245870
B8: Profit Margin | C8: =(C7/C5)*100 -> 15.799627
B9: Total Orders | C9: =GETPIVOTDATA("Order_ID",Pivot_tables!$A$83) -> 600
B10: Return Rate | C10: =GETPIVOTDATA("Order_ID",Pivot_tables!$A$86,"Order_Status","Returned")/Pivot_tables!B90 -> 0.185

Sheet Pivot_tables
A3: Product | B3: Total Revenue | C3: Total Profit | E3: Product | F3: Total Revenue | G3: Total Profit
A4: Conference Table | B4: 580800 | C4: 52800 | E4: =A4 -> Conference Table | F4: =B4 -> 580800 | G4: =C4 -> 52800
A5: Laptop Pro 14 | B5: 361200 | C5: 90300 | E5: =A5 -> Laptop Pro 14 | F5: =B5 -> 361200 | G5: =C5 -> 90300
A6: Standing Desk Pro | B6: 215900 | C6: 38100 | E6: =A6 -> Standing Desk Pro | F6: =B6 -> 215900 | G6: =C6 -> 38100
A7: Tablet Air 10 | B7: 168600 | C7: 22480 | E7: =A7 -> Tablet Air 10 | F7: =B7 -> 168600 | G7: =C7 -> 22480
A8: Wireless Monitor 27 | B8: 122850 | C8: 19110 | E8: =A8 -> Wireless Monitor 27 | F8: =B8 -> 122850 | G8: =C8 -> 19110
A9: Office Chair Deluxe | B9: 87360 | C9: 19110 | E9: =A9 -> Office Chair Deluxe | F9: =B9 -> 87360 | G9: =C9 -> 19110
A10: Ink Cartridge Xl | B10: 10845 | C10: 1205 | E10: =A10 -> Ink Cartridge Xl | F10: =B10 -> 10845 | G10: =C10 -> 1205
A11: Wireless Mouse | B11: 7025 | C11: 1967 | E11: =A11 -> Wireless Mouse | F11: =B11 -> 7025 | G11: =C11 -> 1967
A12: Paper Ream A4 | B12: 1596 | C12: 798 | E12: =A12 -> Paper Ream A4 | F12: =B12 -> 1596 | G12: =C12 -> 798
F13: =SUM(F4:F12) -> 1556176 | G13: =SUM(G4:G12) -> 245870
A15: Regions | B15: Total Revenue | C15: Total Profit | E15: Region | F15: Total Revenue | G15: Total Profit
A16: South America | B16: 155209 | C16: 25657 | E16: =A16 -> South America | F16: =B16 -> 155209 | G16: =C16 -> 25657
A17: North America | B17: 296760 | C17: 47145 | E17: =A17 -> North America | F17: =B17 -> 296760 | G17: =C17 -> 47145
A18: Middle East | B18: 309572 | C18: 48149 | E18: =A18 -> Middle East | F18: =B18 -> 309572 | G18: =C18 -> 48149
A19: Asia-Pacific | B19: 322412 | C19: 50651 | E19: =A19 -> Asia-Pacific | F19: =B19 -> 322412 | G19: =C19 -> 50651
A20: Europe | B20: 472223 | C20: 74268 | E20: =A20 -> Europe | F20: =B20 -> 472223 | G20: =C20 -> 74268
A23: sales_rep | B23: Total Revenue/yr | E23: Sales_rep | F23: Total revenue(2024)
A24: Alex Morgan | B24: 135417 | E24: =A24 -> Alex Morgan | F24: =B24 -> 135417
A25: Daniel Smith | B25: 138928 | E25: =A25 -> Daniel Smith | F25: =B25 -> 138928
A26: Fahad Al Saud | B26: 154299 | E26: =A26 -> Fahad Al Saud | F26: =B26 -> 154299
A27: Jan De Vries | B27: 155209 | E27: =A27 -> Jan De Vries | F27: =B27 -> 155209
A28: Liam Chen | B28: 178996 | E28: =A28 -> Liam Chen | F28: =B28 -> 178996
A29: Lucas Pereira | B29: 161357 | E29: =A29 -> Lucas Pereira | F29: =B29 -> 161357
A30: Marie Dubois | B30: 148215 | E30: =A30 -> Marie Dubois | F30: =B30 -> 148215
A31: Omar Hassan | B31: 185770 | E31: =A31 -> Omar Hassan | F31: =B31 -> 185770
A32: Sophie Klein | B32: 136642 | E32: =A32 -> Sophie Klein | F32: =B32 -> 136642
A33: Wei Zhang | B33: 161343 | E33: =A33 -> Wei Zhang | F33: =B33 -> 161343
A36: Months | B36: Sum of Revenue
A37: Jan | B37: 176113 | E37: Monthly Target
A38: Feb | B38: 134249 | D38: =_xlfn.XLOOKUP(E38,sales_reps[Monthly_Target],sales_reps[Sales_Rep]) -> Alex Morgan | E38: {=_xlfn.XLOOKUP(A38,$A$38:$A$47,sales_reps[Monthly_Target])} -> 120000
A39: Mar | B39: 164835 | D39: =_xlfn.XLOOKUP(E39,sales_reps[Monthly_Target],sales_reps[Sales_Rep]) -> Daniel Smith | E39: {=_xlfn.XLOOKUP(A39,$A$38:$A$47,sales_reps[Monthly_Target])} -> 100000
A40: Apr | B40: 163022 | D40: =_xlfn.XLOOKUP(E40,sales_reps[Monthly_Target],sales_reps[Sales_Rep]) -> Sophie Klein | E40: {=_xlfn.XLOOKUP(A40,$A$38:$A$47,sales_reps[Monthly_Target])} -> 90000
A41: May | B41: 156541 | D41: =_xlfn.XLOOKUP(E41,sales_reps[Monthly_Target],sales_reps[Sales_Rep]) -> Marie Dubois | E41: {=_xlfn.XLOOKUP(A41,$A$38:$A$47,sales_reps[Monthly_Target])} -> 88000
A42: Jun | B42: 136519 | D42: =_xlfn.XLOOKUP(E42,sales_reps[Monthly_Target],sales_reps[Sales_Rep]) -> Jan De Vries | E42: {=_xlfn.XLOOKUP(A42,$A$38:$A$47,sales_reps[Monthly_Target])} -> 87000
A43: Jul | B43: 165478 | D43: =_xlfn.XLOOKUP(E43,sales_reps[Monthly_Target],sales_reps[Sales_Rep]) -> Liam Chen | E43: {=_xlfn.XLOOKUP(A43,$A$38:$A$47,sales_reps[Monthly_Target])} -> 85000
A44: Aug | B44: 139581 | D44: =_xlfn.XLOOKUP(E44,sales_reps[Monthly_Target],sales_reps[Sales_Rep]) -> Wei Zhang | E44: {=_xlfn.XLOOKUP(A44,$A$38:$A$47,sales_reps[Monthly_Target])} -> 92000
A45: Sept | B45: 58932 | D45: =_xlfn.XLOOKUP(E45,sales_reps[Monthly_Target],sales_reps[Sales_Rep]) -> Omar Hassan | E45: {=_xlfn.XLOOKUP(A45,$A$38:$A$47,sales_reps[Monthly_Target])} -> 95000
A46: Oct | B46: 91607 | D46: =_xlfn.XLOOKUP(E46,sales_reps[Monthly_Target],sales_reps[Sales_Rep]) -> Fahad Al Saud | E46: {=_xlfn.XLOOKUP(A46,$A$38:$A$47,sales_reps[Monthly_Target])} -> 98000
A47: Nov | B47: 90370 | D47: =_xlfn.XLOOKUP(E47,sales_reps[Monthly_Target],sales_reps[Sales_Rep]) -> Lucas Pereira | E47: {=_xlfn.XLOOKUP(A47,$A$38:$A$47,sales_reps[Monthly_Target])} -> 70000
A48: Dec | B48: 78929
A60: Customer_segment | B60: Total Revenue | C60: Total Profit
A61: Consumer | B61: 479907 | C61: 77576 | E61: =A61 -> Consumer | F61: =B61 -> 479907 | G61: =C61 -> 77576
A62: Corporate | B62: 599274 | C62: 95189 | E62: =A62 -> Corporate | F62: =B62 -> 599274 | G62: =C62 -> 95189
A63: Small Business | B63: 476995 | C63: 73105 | E63: =A63 -> Small Business | F63: =B63 -> 476995 | G63: =C63 -> 73105
A66: Months | B66: Total Revenue | C66: Total Profit | E66: Months | F66: Total Revenue | G66: Total profit
A67: Jan | B67: 176113 | C67: 24806 | E67: =A67 -> Jan | F67: =B67 -> 176113 | G67: =C67 -> 24806
A68: Feb | B68: 134249 | C68: 22277 | E68: =A68 -> Feb | F68: =B68 -> 134249 | G68: =C68 -> 22277
A69: Mar | B69: 164835 | C69: 26786 | E69: =A69 -> Mar | F69: =B69 -> 164835 | G69: =C69 -> 26786
A70: Apr | B70: 163022 | C70: 25700 | E70: =A70 -> Apr | F70: =B70 -> 163022 | G70: =C70 -> 25700
A71: May | B71: 156541 | C71: 26096 | E71: =A71 -> May | F71: =B71 -> 156541 | G71: =C71 -> 26096
A72: Jun | B72: 136519 | C72: 22863 | E72: =A72 -> Jun | F72: =B72 -> 136519 | G72: =C72 -> 22863
A73: Jul | B73: 165478 | C73: 25866 | E73: =A73 -> Jul | F73: =B73 -> 165478 | G73: =C73 -> 25866
A74: Aug | B74: 139581 | C74: 21896 | E74: =A74 -> Aug | F74: =B74 -> 139581 | G74: =C74 -> 21896
A75: Sept | B75: 58932 | C75: 9316 | E75: =A75 -> Sept | F75: =B75 -> 58932 | G75: =C75 -> 9316
A76: Oct | B76: 91607 | C76: 13048 | E76: =A76 -> Oct | F76: =B76 -> 91607 | G76: =C76 -> 13048
A77: Nov | B77: 90370 | C77: 15115 | E77: =A77 -> Nov | F77: =B77 -> 90370 | G77: =C77 -> 15115
A78: Dec | B78: 78929 | C78: 12101 | E78: =A78 -> Dec | F78: =B78 -> 78929 | G78: =C78 -> 12101
A83: Count of Order_ID
A84: 600
A86: Order status | B86: Count of Order_ID
A87: Completed | B87: 366
A88: Pending | B88: 123
A89: Returned | B89: 111
B90: =SUM(B87:B89) -> 600
A94: Order Month | B94: Quantity
A95: Jan | B95: 62
A96: Feb | B96: 58
A97: Mar | B97: 62
A98: Apr | B98: 60
A99: May | B99: 62
A100: Jun | B100: 60
A101: Jul | B101: 62
A102: Aug | B102: 53
A103: Sept | B103: 30
A104: Oct | B104: 31
A105: Nov | B105: 30
A106: Dec | B106: 30
A112: Country | B112: Total Revenue | C112: Sum of Profit
A113: Australia | B113: 136642 | C113: 22088 | E113: =A113 -> Australia | F113: =B113 -> 136642 | G113: =$C$113 -> 22088
A114: Brazil | B114: 155209 | C114: 25657 | E114: =A114 -> Brazil | F114: =B114 -> 155209 | G114: =$C$113 -> 22088
A115: Canada | B115: 161343 | C115: 24336 | E115: =A115 -> Canada | F115: =B115 -> 161343 | G115: =$C$113 -> 22088
A116: France | B116: 178996 | C116: 25856 | E116: =A116 -> France | F116: =B116 -> 178996 | G116: =$C$113 -> 22088
A117: Germany | B117: 138928 | C117: 23356 | E117: =A117 -> Germany | F117: =B117 -> 138928 | G117: =$C$113 -> 22088
A118: Netherlands | B118: 154299 | C118: 25056 | E118: =A118 -> Netherlands | F118: =B118 -> 154299 | G118: =$C$113 -> 22088
A119: Saudi Arabia | B119: 161357 | C119: 25161 | E119: =A119 -> Saudi Arabia | F119: =B119 -> 161357 | G119: =$C$113 -> 22088
A120: Singapore | B120: 185770 | C120: 28563 | E120: =A120 -> Singapore | F120: =B120 -> 185770 | G120: =$C$113 -> 22088
A121: United Arab Emirates | B121: 148215 | C121: 22988 | E121: =A121 -> United Arab Emirates | F121: =B121 -> 148215 | G121: =$C$113 -> 22088
A122: United States | B122: 135417 | C122: 22809 | E122: =A122 -> United States | F122: =B122 -> 135417 | G122: =$C$113 -> 22088
A125: Country | B125: Total Revenue | C125: Total Profit | D125: Total Cost
A126: Australia | B126: 136642 | C126: 22088 | D126: 114554
A127: Brazil | B127: 155209 | C127: 25657 | D127: 129552
A128: Canada | B128: 161343 | C128: 24336 | D128: 137007
A129: France | B129: 178996 | C129: 25856 | D129: 153140
A130: Germany | B130: 138928 | C130: 23356 | D130: 115572
A131: Netherlands | B131: 154299 | C131: 25056 | D131: 129243
A132: Saudi Arabia | B132: 161357 | C132: 25161 | D132: 136196
A133: Singapore | B133: 185770 | C133: 28563 | D133: 157207
A134: United Arab Emirates | B134: 148215 | C134: 22988 | D134: 125227
A135: United States | B135: 135417 | C135: 22809 | D135: 112608

Sheet Dashboard
